aw_watcher_lid/__init__.py
aw_watcher_lid/__main__.py
aw_watcher_lid/boot_detector.py
aw_watcher_lid/config.py
aw_watcher_lid/dbus_listener.py
aw_watcher_lid/journal_listener.py
aw_watcher_lid/lid.py
aw_watcher_lid-0.1.2.dist-info/METADATA
aw_watcher_lid-0.1.2.dist-info/WHEEL
aw_watcher_lid-0.1.2.dist-info/entry_points.txt
aw_watcher_lid-0.1.2.dist-info/licenses/LICENSE
aw_watcher_lid-0.1.2.dist-info/RECORD
