Metadata-Version: 2.4
Name: aw-watcher-lid
Version: 0.1.2
Summary: ActivityWatch watcher for laptop lid events and system suspend/resume
License: MPL-2.0
License-File: LICENSE
Keywords: activitywatch,watcher,laptop,lid,suspend,time-tracking
Author: Tobias Brox
Author-email: tobias@redpill-linpro.com
Requires-Python: >=3.13,<4.0
Classifier: Development Status :: 4 - Beta
Classifier: Intended Audience :: End Users/Desktop
Classifier: License :: OSI Approved
Classifier: Programming Language :: Python :: 3
Classifier: Programming Language :: Python :: 3.13
Classifier: Programming Language :: Python :: 3.14
Classifier: Topic :: Utilities
Requires-Dist: PyGObject (>=3.42.0,<4.0.0)
Requires-Dist: aw-client (>=0.5.13,<0.6.0)
Requires-Dist: dbus-python (>=1.3.2,<2.0.0)
Project-URL: Homepage, https://github.com/tobixen/aw-watcher-lid
Project-URL: Repository, https://github.com/tobixen/aw-watcher-lid
